sqimple/__init__.py
sqimple/cli.py
sqimple/db.py
sqimple/main.py
sqimple/webapp.py
sqimple/static/ace.js
sqimple/static/main.js
sqimple/static/mode-sql.js
sqimple/static/style.css
sqimple/templates/index.html
sqimple-0.1.1.dist-info/entry_points.txt
sqimple-0.1.1.dist-info/LICENSE
sqimple-0.1.1.dist-info/WHEEL
sqimple-0.1.1.dist-info/METADATA
sqimple-0.1.1.dist-info/RECORD
