Metadata-Version: 2.1
Name: sqimple
Version: 0.1.1
Summary: Simple SQL Web Interface
Author: Zach Gulde
Author-email: zachgulde@gmail.com
Classifier: License :: OSI Approved :: MIT License
Requires-Dist: Flask==1.1
Requires-Dist: waitress==2.0
